transformer_nuggets/__init__.py
transformer_nuggets/subclass.py
transformer_nuggets/flash/__init__.py
transformer_nuggets/flash/flash_attention.py
transformer_nuggets/flash/masks.py
transformer_nuggets/flex/__init__.py
transformer_nuggets/fp8/__init__.py
transformer_nuggets/fp8/fp8_matmul.py
transformer_nuggets/fp8/scaled_quant.py
transformer_nuggets/helion/__init__.py
transformer_nuggets/helion/utils.py
transformer_nuggets/llama/README.md
transformer_nuggets/llama/__init__.py
transformer_nuggets/llama/finetune.py
transformer_nuggets/llama/model.py
transformer_nuggets/llama/prepare_data.py
transformer_nuggets/llama/tokenizer.py
transformer_nuggets/llama/train.py
transformer_nuggets/misc/__init__.py
transformer_nuggets/misc/mlp.py
transformer_nuggets/misc/swizzler.py
transformer_nuggets/moe/__init__.py
transformer_nuggets/moe/unrolled.py
transformer_nuggets/mx/__init__.py
transformer_nuggets/mx/to_blocked.py
transformer_nuggets/quant/__init__.py
transformer_nuggets/quant/dequant_kernel.py
transformer_nuggets/quant/nf4_tensor.py
transformer_nuggets/quant/qlora.py
transformer_nuggets/quant/qlora_debug.py
transformer_nuggets/utils/__init__.py
transformer_nuggets/utils/benchmark.py
transformer_nuggets/utils/shape_trace.py
transformer_nuggets/utils/tracing.py
transformer_nuggets/utils/triton.py
transformer_nuggets-0.0.2.dist-info/METADATA
transformer_nuggets-0.0.2.dist-info/WHEEL
transformer_nuggets-0.0.2.dist-info/licenses/LICENSE
transformer_nuggets-0.0.2.dist-info/RECORD
