Metadata-Version: 2.4
Name: transformer_nuggets
Version: 0.0.2
Summary: A place to store reusable transformer components found around the interwebs
Author-email: Driss Guessous <drisspguessous@gmail.com>
License-File: LICENSE
Classifier: License :: OSI Approved :: MIT License
Classifier: Operating System :: OS Independent
Classifier: Programming Language :: Python :: 3
Requires-Python: >=3.10
Requires-Dist: matplotlib
Requires-Dist: pandas
Requires-Dist: rich==13.7.1
Requires-Dist: scipy>=1.9.1
Requires-Dist: tabulate>=0.8
Requires-Dist: torch
Requires-Dist: tqdm>=4.66
Provides-Extra: dev
Requires-Dist: bumpver; extra == 'dev'
Requires-Dist: docstring-parser; extra == 'dev'
Requires-Dist: jsonargparse; extra == 'dev'
Requires-Dist: pip-tools; extra == 'dev'
Requires-Dist: pre-commit==3.6.0; extra == 'dev'
Requires-Dist: pytest; extra == 'dev'
Requires-Dist: ruff; extra == 'dev'
Provides-Extra: flash
Requires-Dist: triton; extra == 'flash'
Provides-Extra: llama
Requires-Dist: datasets==2.15.0; extra == 'llama'
Requires-Dist: fire==0.5.0; extra == 'llama'
Requires-Dist: float8-experimental; extra == 'llama'
Requires-Dist: sentencepiece==0.1.99; extra == 'llama'
Provides-Extra: qlora
Requires-Dist: bitsandbytes; extra == 'qlora'
